rakuten_pay/__init__.py
rakuten_pay/category.py
rakuten_pay/charge.py
rakuten_pay/checkout.py
rakuten_pay/handler_request.py
rakuten_pay/routes/__init__.py
rakuten_pay/routes/base_routes.py
rakuten_pay/routes/category_routes.py
rakuten_pay/routes/charge_routes.py
rakuten_pay/routes/checkout_routes.py
tests/__init__.py
tests/test_category.py
tests/test_charge.py
tests/test_checkout.py
rakuten_pay-0.0.5.dist-info/METADATA
rakuten_pay-0.0.5.dist-info/WHEEL
rakuten_pay-0.0.5.dist-info/top_level.txt
rakuten_pay-0.0.5.dist-info/RECORD
